<?xml version="1.0" encoding="UTF-8" standalone="yes"?>
<oai_dc:dc xmlns:dc="http://purl.org/dc/elements/1.1/" xmlns:oai_dc="http://www.openarchives.org/OAI/2.0/oai_dc/" xmlns:xsi="http://www.w3.org/2001/XMLSchema-instance" xsi:schemaLocation="http://www.openarchives.org/OAI/2.0/oai_dc/ http://www.openarchives.org/OAI/2.0/oai_dc.xsd">
  <dc:identifier>https://scholia.toolforge.org/work/Q111838411</dc:identifier>
  <dc:identifier>http://www.wikidata.org/entity/Q111838411</dc:identifier>
  <dc:identifier>doi:10.2208/JSCEJER.76.7_III_349</dc:identifier>
  <dc:title>ANALYSIS OF IMPACT FACTORS ON REPRODUCTION FROM FRAGMENTS OF INVASIVE ALIAN SPECIES &lt;i&gt;Ludwigia grandiflora&lt;/i&gt;</dc:title>
  <dc:creator>TANAKA, Shuhei</dc:creator>
  <dc:creator>OSHIMA, Yasuhiro</dc:creator>
  <dc:creator>HASEGAWA, Tatsuro</dc:creator>
  <dc:creator>TAKAMI, Wataru</dc:creator>
  <dc:creator>ZHANG, Hongwei</dc:creator>
  <dc:creator>WATABE, Yuki</dc:creator>
  <dc:creator>TABUCHI, Tomoya</dc:creator>
  <dc:creator>NISHIKAWA, Hiroaki</dc:creator>
  <dc:creator>FUJII, Shigeo</dc:creator>
  <dc:type>journal article</dc:type>
  <dc:date>2021-03-16</dc:date>
  <dc:subject>theme:invasion impact</dc:subject>
  <dc:subject>theme:wikidata.org/entity/Q112148709</dc:subject>
  <dc:subject>Ludwigia grandiflora</dc:subject>
  <dc:subject>invasive species</dc:subject>
  <dc:subject>invasion impact</dc:subject>
  <dc:publisher>Japan Society of Civil Engineers</dc:publisher>
</oai_dc:dc>