<?xml version="1.0" encoding="UTF-8" standalone="yes"?>
<oai_dc:dc xmlns:dc="http://purl.org/dc/elements/1.1/" xmlns:oai_dc="http://www.openarchives.org/OAI/2.0/oai_dc/" xmlns:xsi="http://www.w3.org/2001/XMLSchema-instance" xsi:schemaLocation="http://www.openarchives.org/OAI/2.0/oai_dc/ http://www.openarchives.org/OAI/2.0/oai_dc.xsd">
  <dc:identifier>https://scholia.toolforge.org/work/Q56333917</dc:identifier>
  <dc:identifier>http://www.wikidata.org/entity/Q56333917</dc:identifier>
  <dc:identifier>doi:10.1017/S0030605315001039</dc:identifier>
  <dc:title>Human impacts on two endemic cassowary species in Indonesian New Guinea</dc:title>
  <dc:creator>Brodie, Jedediah F.</dc:creator>
  <dc:creator>Pangau-Adam, Margaretha</dc:creator>
  <dc:type>journal article</dc:type>
  <dc:date>2015-11-10</dc:date>
  <dc:subject>theme:invasion impact</dc:subject>
  <dc:subject>theme:wikidata.org/entity/Q112148709</dc:subject>
  <dc:subject>invasion impact</dc:subject>
  <dc:subject>New Guinea</dc:subject>
  <dc:subject>Northern Cassowary</dc:subject>
  <dc:subject>Dwarf Cassowary</dc:subject>
  <dc:subject>ecological disturbance</dc:subject>
  <dc:subject>seed dispersal</dc:subject>
  <dc:subject>population ecology</dc:subject>
  <dc:subject>altitude</dc:subject>
  <dc:subject>abundance</dc:subject>
  <dc:subject>razorback</dc:subject>
  <dc:subject>hunting regulation</dc:subject>
  <dc:subject>camera trap</dc:subject>
  <dc:subject>spatial scale</dc:subject>
  <dc:publisher>Cambridge University Press (CUP)</dc:publisher>
</oai_dc:dc>