<?xml version="1.0" encoding="UTF-8" standalone="yes"?>
<oai_dc:dc xmlns:dc="http://purl.org/dc/elements/1.1/" xmlns:oai_dc="http://www.openarchives.org/OAI/2.0/oai_dc/" xmlns:xsi="http://www.w3.org/2001/XMLSchema-instance" xsi:schemaLocation="http://www.openarchives.org/OAI/2.0/oai_dc/ http://www.openarchives.org/OAI/2.0/oai_dc.xsd">
  <dc:identifier>https://scholia.toolforge.org/work/Q37554273</dc:identifier>
  <dc:identifier>http://www.wikidata.org/entity/Q37554273</dc:identifier>
  <dc:identifier>doi:10.1603/029.102.0301</dc:identifier>
  <dc:title>Potential of "lure and kill" in long-term pest management and eradication of invasive species</dc:title>
  <dc:creator>El-Sayed, Ashraf M</dc:creator>
  <dc:creator>Suckling, David Maxwell</dc:creator>
  <dc:creator>Byers, J A</dc:creator>
  <dc:creator>Jang, E B</dc:creator>
  <dc:creator>Wearing, C H</dc:creator>
  <dc:type>journal article</dc:type>
  <dc:date>2009-06-01</dc:date>
  <dc:language>en</dc:language>
  <dc:subject>theme:invasion management</dc:subject>
  <dc:subject>theme:wikidata.org/entity/Q113019190</dc:subject>
  <dc:subject>invasion biology</dc:subject>
  <dc:subject>invasive species</dc:subject>
  <dc:subject>invasive species eradication</dc:subject>
  <dc:subject>invasive species management</dc:subject>
  <dc:subject>invasion management</dc:subject>
  <dc:publisher>Oxford University Press (OUP)</dc:publisher>
  <dc:coverage>n/a</dc:coverage>
</oai_dc:dc>