<?xml version="1.0" encoding="UTF-8" standalone="yes"?>
<oai_dc:dc xmlns:dc="http://purl.org/dc/elements/1.1/" xmlns:oai_dc="http://www.openarchives.org/OAI/2.0/oai_dc/" xmlns:xsi="http://www.w3.org/2001/XMLSchema-instance" xsi:schemaLocation="http://www.openarchives.org/OAI/2.0/oai_dc/ http://www.openarchives.org/OAI/2.0/oai_dc.xsd">
  <dc:identifier>https://scholia.toolforge.org/work/Q110630255</dc:identifier>
  <dc:identifier>http://www.wikidata.org/entity/Q110630255</dc:identifier>
  <dc:identifier>doi:10.1016/J.SAJB.2015.03.019</dc:identifier>
  <dc:title>Explaining invasion success of non-native trees in Southern Africa</dc:title>
  <dc:creator>Bezeng, S.B.</dc:creator>
  <dc:creator>Davies, T.J.</dc:creator>
  <dc:creator>Yessoufou, K.</dc:creator>
  <dc:creator>Van Der Bank, M.</dc:creator>
  <dc:type>journal article</dc:type>
  <dc:date>2015-05</dc:date>
  <dc:subject>theme:invasion success</dc:subject>
  <dc:subject>theme:wikidata.org/entity/Q109467185</dc:subject>
  <dc:subject>invasion success</dc:subject>
  <dc:publisher>Elsevier BV</dc:publisher>
</oai_dc:dc>