<?xml version="1.0" encoding="UTF-8" standalone="yes"?>
<oai_dc:dc xmlns:dc="http://purl.org/dc/elements/1.1/" xmlns:oai_dc="http://www.openarchives.org/OAI/2.0/oai_dc/" xmlns:xsi="http://www.w3.org/2001/XMLSchema-instance" xsi:schemaLocation="http://www.openarchives.org/OAI/2.0/oai_dc/ http://www.openarchives.org/OAI/2.0/oai_dc.xsd">
  <dc:identifier>http://www.wikidata.org/entity/Q110663953</dc:identifier>
  <dc:identifier>doi:10.3897/NEOBIOTA.57.52195</dc:identifier>
  <dc:title>Spatiotemporal patterns of non-native terrestrial gastropods in the contiguous United States</dc:title>
  <dc:creator>Gladstone, Nicholas S.</dc:creator>
  <dc:creator>Bordeau, Trystan A.</dc:creator>
  <dc:creator>Leppanen, Christy</dc:creator>
  <dc:creator>McKinney, Michael L.</dc:creator>
  <dc:type>journal article</dc:type>
  <dc:date>2020-06-17</dc:date>
  <dc:language>en</dc:language>
  <dc:rights>http://creativecommons.org/licenses/by/4.0/</dc:rights>
  <dc:publisher>Pensoft Publishers</dc:publisher>
</oai_dc:dc>