<?xml version="1.0" encoding="UTF-8" standalone="yes"?>
<oai_dc:dc xmlns:dc="http://purl.org/dc/elements/1.1/" xmlns:oai_dc="http://www.openarchives.org/OAI/2.0/oai_dc/" xmlns:xsi="http://www.w3.org/2001/XMLSchema-instance" xsi:schemaLocation="http://www.openarchives.org/OAI/2.0/oai_dc/ http://www.openarchives.org/OAI/2.0/oai_dc.xsd">
  <dc:identifier>https://scholia.toolforge.org/work/Q111108772</dc:identifier>
  <dc:identifier>http://www.wikidata.org/entity/Q111108772</dc:identifier>
  <dc:identifier>doi:10.3759/TROPICS.20.45</dc:identifier>
  <dc:title>Impact of Acacia nilotica (L.) Willd. ex Del invasion on plant species diversity in the Bekol Savanna, Baluran National Park, East Java, Indonesia</dc:title>
  <dc:creator>Caesariantika, Efsa</dc:creator>
  <dc:creator>Kondo, Toshiaki</dc:creator>
  <dc:creator>Nakagoshi, Nobukazu</dc:creator>
  <dc:type>journal article</dc:type>
  <dc:date>2011</dc:date>
  <dc:language>en</dc:language>
  <dc:subject>theme:invasion impact</dc:subject>
  <dc:subject>theme:wikidata.org/entity/Q112148709</dc:subject>
  <dc:subject>Acacia nilotica</dc:subject>
  <dc:subject>invasive species</dc:subject>
  <dc:subject>invasion impact</dc:subject>
  <dc:publisher>The Japan Society of Tropical Ecology</dc:publisher>
</oai_dc:dc>