<?xml version="1.0" encoding="UTF-8" standalone="yes"?>
<oai_dc:dc xmlns:dc="http://purl.org/dc/elements/1.1/" xmlns:oai_dc="http://www.openarchives.org/OAI/2.0/oai_dc/" xmlns:xsi="http://www.w3.org/2001/XMLSchema-instance" xsi:schemaLocation="http://www.openarchives.org/OAI/2.0/oai_dc/ http://www.openarchives.org/OAI/2.0/oai_dc.xsd">
  <dc:identifier>https://scholia.toolforge.org/work/Q39017065</dc:identifier>
  <dc:identifier>http://www.wikidata.org/entity/Q39017065</dc:identifier>
  <dc:identifier>doi:10.1111/AOGS.13095</dc:identifier>
  <dc:title>Impact of microbial invasion of amniotic cavity and the type of microorganisms on short-term neonatal outcome in women with preterm labor and intact membranes</dc:title>
  <dc:creator>Cobo, Teresa</dc:creator>
  <dc:creator>Vives, Irene</dc:creator>
  <dc:creator>Rodríguez-Trujillo, Adriano</dc:creator>
  <dc:creator>Murillo, Clara</dc:creator>
  <dc:creator>Ángeles, Martina A</dc:creator>
  <dc:creator>Mestres, Jordi Bosch</dc:creator>
  <dc:creator>Vergara, Andrea</dc:creator>
  <dc:creator>Gratacós, Eduard</dc:creator>
  <dc:creator>Palacio, Montse</dc:creator>
  <dc:type>journal article</dc:type>
  <dc:date>2017-01-17</dc:date>
  <dc:language>en</dc:language>
  <dc:subject>theme:invasion impact</dc:subject>
  <dc:subject>theme:wikidata.org/entity/Q112148709</dc:subject>
  <dc:subject>microbial invasion</dc:subject>
  <dc:subject>invasion impact</dc:subject>
  <dc:publisher>Wiley</dc:publisher>
</oai_dc:dc>