<?xml version="1.0" encoding="UTF-8" standalone="yes"?>
<oai_dc:dc xmlns:dc="http://purl.org/dc/elements/1.1/" xmlns:oai_dc="http://www.openarchives.org/OAI/2.0/oai_dc/" xmlns:xsi="http://www.w3.org/2001/XMLSchema-instance" xsi:schemaLocation="http://www.openarchives.org/OAI/2.0/oai_dc/ http://www.openarchives.org/OAI/2.0/oai_dc.xsd">
  <dc:identifier>https://scholia.toolforge.org/work/Q114940283</dc:identifier>
  <dc:identifier>http://www.wikidata.org/entity/Q114940283</dc:identifier>
  <dc:identifier>doi:10.1086/699433</dc:identifier>
  <dc:title>&lt;i&gt;Ecology and Management of Terrestrial Vertebrate Invasive Species in the United States&lt;/i&gt;. Edited by William C. Pitt, James C. Beasley, and Gary W. Witmer. Boca Raton (Florida): CRC Press (Taylor &amp; Francis Group). $99.95. xii + 403 p.; ill.; index. ISBN: 9781498704823. 2018.</dc:title>
  <dc:creator>Gibbons, J. Whitfield</dc:creator>
  <dc:type>journal article</dc:type>
  <dc:date>2018-09-15</dc:date>
  <dc:subject>theme:invasion management</dc:subject>
  <dc:subject>theme:wikidata.org/entity/Q113019190</dc:subject>
  <dc:subject>invasive species</dc:subject>
  <dc:subject>invasion management</dc:subject>
  <dc:publisher>University of Chicago Press</dc:publisher>
</oai_dc:dc>